jpmml_evaluator/__init__.py
jpmml_evaluator/__main__.py
jpmml_evaluator/cli.py
jpmml_evaluator/jpype.py
jpmml_evaluator/metadata.py
jpmml_evaluator/py4j.py
jpmml_evaluator/pyjnius.py
jpmml_evaluator/dependencies/__init__.py
jpmml_evaluator/dependencies/codemodel-4.0.5.jar
jpmml_evaluator/dependencies/commons-math3-3.6.1.jar
jpmml_evaluator/dependencies/failureaccess-1.0.3.jar
jpmml_evaluator/dependencies/fastcsv-3.6.0.jar
jpmml_evaluator/dependencies/guava-33.5.0-jre.jar
jpmml_evaluator/dependencies/istack-commons-runtime-4.1.2.jar
jpmml_evaluator/dependencies/jackson-annotations-2.19.4.jar
jpmml_evaluator/dependencies/jakarta.activation-api-2.1.4.jar
jpmml_evaluator/dependencies/jakarta.xml.bind-api-4.0.4.jar
jpmml_evaluator/dependencies/jaxb-core-4.0.6.jar
jpmml_evaluator/dependencies/jaxb-runtime-4.0.6.jar
jpmml_evaluator/dependencies/jpmml-codemodel-1.2.0.jar
jpmml_evaluator/dependencies/pickle-1.5.jar
jpmml_evaluator/dependencies/pmml-converter-1.6.5.jar
jpmml_evaluator/dependencies/pmml-evaluator-1.7.6.jar
jpmml_evaluator/dependencies/pmml-evaluator-metro-1.7.6.jar
jpmml_evaluator/dependencies/pmml-evaluator-reporting-1.7.6.jar
jpmml_evaluator/dependencies/pmml-model-1.7.6.jar
jpmml_evaluator/dependencies/pmml-model-metro-1.7.6.jar
jpmml_evaluator/dependencies/pmml-python-1.3.11.jar
jpmml_evaluator/dependencies/pmml-transpiler-1.4.7.jar
jpmml_evaluator/dependencies/serpent-1.40.jar
jpmml_evaluator/dependencies/slf4j-api-2.0.17.jar
jpmml_evaluator/dependencies/slf4j-jdk14-2.0.17.jar
jpmml_evaluator/resources/__init__.py
jpmml_evaluator/resources/jpmml-evaluator-python-1.5-SNAPSHOT.jar
jpmml_evaluator-0.15.4.dist-info/licenses/LICENSE.txt
jpmml_evaluator-0.15.4.dist-info/licenses/NOTICE.txt
jpmml_evaluator-0.15.4.dist-info/METADATA
jpmml_evaluator-0.15.4.dist-info/WHEEL
jpmml_evaluator-0.15.4.dist-info/entry_points.txt
jpmml_evaluator-0.15.4.dist-info/top_level.txt
jpmml_evaluator-0.15.4.dist-info/RECORD
