Metadata-Version: 2.4
Name: jpmml_evaluator
Version: 0.15.4
Summary: PMML evaluator library for Python
Home-page: https://github.com/jpmml/jpmml-evaluator-python
Download-URL: https://github.com/jpmml/jpmml-evaluator-python/archive/0.15.4.tar.gz
Author: Villu Ruusmann
Author-email: villu.ruusmann@gmail.com
License: GNU Affero General Public License (AGPL) version 3.0
Requires-Python: >=3.8
License-File: LICENSE.txt
License-File: NOTICE.txt
Requires-Dist: jpype1
Requires-Dist: pandas
Requires-Dist: py4j
Requires-Dist: pyjnius>=1.2.1
Dynamic: author
Dynamic: author-email
Dynamic: download-url
Dynamic: home-page
Dynamic: license
Dynamic: license-file
Dynamic: requires-dist
Dynamic: requires-python
Dynamic: summary
